ipatool_py/__init__.py
ipatool_py/itunes.py
ipatool_py/store.py
ipatool_py/schemas/README.md
ipatool_py/schemas/__init__.py
ipatool_py/schemas/itunes_lookup_resp.py
ipatool_py/schemas/store_authenticate_req.py
ipatool_py/schemas/store_authenticate_resp.py
ipatool_py/schemas/store_buyproduct_req.py
ipatool_py/schemas/store_buyproduct_resp.py
ipatool_py/schemas/store_download_req.py
ipatool_py/schemas/store_download_resp.py
reqs/__init__.py
reqs/itunes.py
reqs/store.py
ak_ipatool_py-0.0.5.dist-info/METADATA
ak_ipatool_py-0.0.5.dist-info/WHEEL
ak_ipatool_py-0.0.5.dist-info/entry_points.txt
ak_ipatool_py-0.0.5.dist-info/top_level.txt
ak_ipatool_py-0.0.5.dist-info/RECORD
