Metadata-Version: 2.1
Name: ak-ipatool-py
Version: 0.0.5
Summary: Appknox forked ipatoolpy is a command line tool that allows you to search for iOS apps on the App Store and download a copy of the app package, known as an ipa file.
Home-page: https://github.com/appknox/ak-ipatool-py
Author: appknox
Author-email: engineering@appknox.com
Requires-Python: >=3.7
Requires-Dist: setuptools
Requires-Dist: requests
Requires-Dist: rich
